Metadata-Version: 2.1
Name: xd-cwl-utils
Version: 0.2.1
Summary: Tool for managing CWL file repositories.
Home-page: https://github.com/xDBio-Inc/xd-cwl-utils
Author: Karl Sebby
Author-email: karl.sebby@xdbio.com
License: Apache 2.0
Platform: UNKNOWN
Classifier: Development Status :: 3 - Alpha
Classifier: License :: OSI Approved :: Apache Software License
Requires-Python: >=3
Requires-Dist: setuptools
Requires-Dist: requests
Requires-Dist: ruamel.yaml (<=0.16,>=0.15)
Requires-Dist: semantic-version
Requires-Dist: pandoc-include
Requires-Dist: cwltool
